pyctmo/__init__.py
pyctmo/__main__.py
pyctmo/db/__init__.py
pyctmo/db/data_parser.py
pyctmo/db/db_helper.py
pyctmo/db/mysqldriver.py
pyctmo/db/postgresqldriver.py
pyctmo/simulation/__init__.py
pyctmo/simulation/simfinder.py
pyctmo/simulation/simsaver.py
pyctmo/stats/__init__.py
pyctmo/stats/statsfiles_runner.py
pyctmo/stats/statslogic.py
pyctmo/tests/__init__.py
pyctmo/tests/test_configunpacker.py
pyctmo/tests/test_sim_finder.py
pyctmo/tests/test_sim_saver.py
pyctmo/tests/test_statslogic.py
pyctmo/utils/__init__.py
pyctmo/utils/configs_unpacker.py
pyctmo/utils/simplelog.py
pyctmo/utils/slmc_helper.py
pyctmo-1.4.0.dist-info/LICENSE
pyctmo-1.4.0.dist-info/METADATA
pyctmo-1.4.0.dist-info/WHEEL
pyctmo-1.4.0.dist-info/top_level.txt
pyctmo-1.4.0.dist-info/RECORD
